xonsh_kernel/__init__.py
xonsh_kernel/__main__.py
xonsh_kernel/install.py
xonsh_kernel/kernel.py
xonsh_kernel-0.4.1.dist-info/METADATA
xonsh_kernel-0.4.1.dist-info/WHEEL
xonsh_kernel-0.4.1.dist-info/RECORD
