Metadata-Version: 1.2
Name: xonsh_kernel
Version: 0.4.1
Summary: An Xonsh kernel for Jupyter
Home-page: https://github.com/calysto/xonsh_kernel
License: UNKNOWN
Author: Steven Silvester
Author-email: steven.silvester@ieee.org
Classifier: Framework :: IPython
Classifier: License :: OSI Approved :: BSD License
Classifier: Programming Language :: Python :: 2
Classifier: Programming Language :: Python :: 3
Classifier: Topic :: System :: Shells
Requires-Dist: metakernel (>=0.10.5)
Requires-Dist: xonsh
